Metadata-Version: 2.4
Name: PyWebDAV3-GNUHealth
Version: 0.13.0
Summary: WebDAV library for Python3 - GNU Health port
Home-page: https://www.gnuhealth.org
Download-URL: https://ftp.gnu.org/gnu/health/
Author: GNU Solidario
Author-email: health@gnusolidario.org
Maintainer: GNU Health team
Maintainer-email: info@gnuhealth.org
License: GPL v3
Keywords: webdav,GNUHealth,server,dav,standalone,library,gpl,http,rfc2518,rfc 2518
Platform: Unix
Classifier: Development Status :: 4 - Beta
Classifier: Environment :: Console
Classifier: Environment :: Web Environment
Classifier: Intended Audience :: Developers
Classifier: Intended Audience :: System Administrators
Classifier: License :: OSI Approved :: GNU General Public License (GPL)
Classifier: Operating System :: POSIX
Classifier: Programming Language :: Python
Classifier: Topic :: Software Development :: Libraries
Dynamic: author
Dynamic: author-email
Dynamic: classifier
Dynamic: description
Dynamic: download-url
Dynamic: home-page
Dynamic: keywords
Dynamic: license
Dynamic: maintainer
Dynamic: maintainer-email
Dynamic: platform
Dynamic: summary
